__init__.py
_version.py
arguments.py
main.py
searchpie/__init__.py
searchpie/searchpie.py
searchpie/data/configure.json
searchpie/functions/__init__.py
searchpie/functions/mal.py
searchpie/functions/tmdb.py
searchpie/functions/wiki.py
searchpie/functions/helpers/DataClass.py
searchpie/functions/helpers/__init__.py
searchpie/functions/helpers/iso_language_codes.py
searchpie-1.0.0.dist-info/LICENSE
searchpie-1.0.0.dist-info/METADATA
searchpie-1.0.0.dist-info/WHEEL
searchpie-1.0.0.dist-info/entry_points.txt
searchpie-1.0.0.dist-info/top_level.txt
searchpie-1.0.0.dist-info/RECORD
