Metadata-Version: 2.1
Name: searchpie
Version: 1.0.0
Summary: A handy tool to search through Wikipedia, Tmdb and Mal.
Download-URL: http://pypi.python.org/pypi/searchpie
Author: Gautam Dhingra
Author-email: gautamdhingra8404@gmail.com
License: MIT
Project-URL: Source, https://github.com/gautam8404/Searchpie
Classifier: Programming Language :: Python :: 3
Classifier: License :: OSI Approved :: MIT License
Classifier: Operating System :: OS Independent
Requires-Python: >=3.5
License-File: LICENSE
Requires-Dist: requests
